{"abilities":["intimidate","flash-fire"],"base_stats":["90","110","80","100","80","95"],"evolution_chain_id":25,"evs":["0","2","0","0","0","0"],"front_female_sprite_default":"No female sprite default found.","front_female_sprite_shiny":"No female sprite shiny found.","front_sprite_default":"https://raw.githubusercontent.com/PokeAPI/sprites/master/sprites/pokemon/59.png","front_sprite_shiny":"https://raw.githubusercontent.com/PokeAPI/sprites/master/sprites/pokemon/shiny/59.png","games":["diamond","ultra","colosseum","x","scarlet","yellow","black","sun","emerald","gold","heartgold","lets","xd","crystal","firered","brilliant","platinum","red","ruby","omega","sword"],"height":19,"hidden_ability":"justified","id":59,"moves":{"black-2-white-2":{"egg":[],"level-up":[["extreme-speed","34"],["roar","1"],["odor-sleuth","1"],["fire-fang","1"],["thunder-fang","1"],["bite","1"]],"machine":[["overheat",""],["giga-impact",""],["flame-charge",""],["dig",""],["swagger",""],["return",""],["hyper-beam",""],["facade",""],["roar",""],["rest",""],["will-o-wisp",""],["safeguard",""],["sunny-day",""],["snarl",""],["bulldoze",""],["incinerate",""],["flamethrower",""],["fire-blast",""],["aerial-ace",""],["attract",""],["substitute",""],["frustration",""],["toxic",""],["double-team",""],["thief",""],["solar-beam",""],["rock-smash",""],["wild-charge",""],["hidden-power",""],["retaliate",""],["strength",""],["round",""],["protect",""]],"tutor":[["heat-wave",""],["covet",""],["outrage",""],["snore",""],["dragon-pulse",""],["helping-hand",""],["iron-head",""],["sleep-talk",""],["iron-tail",""]]},"black-white":{"egg":[],"level-up":[["odor-sleuth","1"],["bite","1"],["thunder-fang","1"],["roar","1"],["fire-fang","1"],["extreme-speed","39"]],"machine":[["sunny-day",""],["hidden-power",""],["snarl",""],["aerial-ace",""],["solar-beam",""],["hyper-beam",""],["bulldoze",""],["toxic",""],["will-o-wisp",""],["facade",""],["flamethrower",""],["wild-charge",""],["giga-impact",""],["safeguard",""],["dig",""],["frustration",""],["retaliate",""],["roar",""],["strength",""],["incinerate",""],["rock-smash",""],["rest",""],["swagger",""],["attract",""],["flame-charge",""],["substitute",""],["overheat",""],["return",""],["round",""],["thief",""],["fire-blast",""],["protect",""],["double-team",""]],"tutor":[]},"brilliant-diamond-and-shining-pearl":{"egg":[],"level-up":[["extreme-speed","1"],["fire-fang","1"],["play-rough","1"],["flare-blitz","1"],["roar","1"],["howl","1"],["crunch","1"],["reversal","1"],["extreme-speed","0"],["bite","1"],["agility","1"],["retaliate","1"],["take-down","1"],["ember","1"],["helping-hand","1"],["burn-up","1"],["flamethrower","1"],["leer","1"],["flame-wheel","1"]],"machine":[["roar",""],["attract",""],["snarl",""],["swagger",""],["will-o-wisp",""],["solar-beam",""],["rest",""],["overheat",""],["safeguard",""],["rock-smash",""],["rock-climb",""],["dragon-pulse",""],["sleep-talk",""],["thief",""],["aerial-ace",""],["strength",""],["sunny-day",""],["bulldoze",""],["protect",""],["iron-tail",""],["substitute",""],["dig",""],["flamethrower",""],["double-team",""],["giga-impact",""],["facade",""],["fire-blast",""],["hyper-beam",""],["endure",""]],"tutor":[]},"colosseum":{"egg":[],"level-up":[["ember","1"],["bite","1"],["extreme-speed","49"],["odor-sleuth","1"],["roar","1"]],"machine":[["strength",""],["hyper-beam",""],["return",""],["hidden-power",""],["rest",""],["roar",""],["toxic",""],["flamethrower",""],["dig",""],["double-team",""],["thief",""],["frustration",""],["iron-tail",""],["rock-smash",""],["fire-blast",""],["sunny-day",""],["facade",""],["secret-power",""],["overheat",""],["aerial-ace",""],["protect",""],["attract",""]],"tutor":[]},"crystal":{"egg":[],"level-up":[["take-down","1"],["roar","1"],["flame-wheel","1"],["extreme-speed","50"],["leer","1"]],"machine":[["dragon-breath",""],["fire-blast",""],["headbutt",""],["sleep-talk",""],["double-team",""],["hidden-power",""],["rock-smash",""],["attract",""],["swift",""],["snore",""],["iron-tail",""],["curse",""],["toxic",""],["sunny-day",""],["endure",""],["roar",""],["hyper-beam",""],["rest",""],["swagger",""],["dig",""],["return",""],["frustration",""],["protect",""]],"tutor":[["flamethrower",""]]},"diamond-pearl":{"egg":[],"level-up":[["roar","1"],["bite","1"],["extreme-speed","39"],["fire-fang","1"],["odor-sleuth","1"],["thunder-fang","1"]],"machine":[["rock-smash",""],["double-team",""],["dragon-pulse",""],["flamethrower",""],["rock-climb",""],["hyper-beam",""],["fire-blast",""],["will-o-wisp",""],["aerial-ace",""],["strength",""],["giga-impact",""],["roar",""],["dig",""],["frustration",""],["toxic",""],["overheat",""],["endure",""],["natural-gift",""],["swagger",""],["sunny-day",""],["attract",""],["substitute",""],["thief",""],["return",""],["iron-tail",""],["secret-power",""],["captivate",""],["facade",""],["protect",""],["sleep-talk",""],["solar-beam",""],["hidden-power",""],["rest",""]],"tutor":[]},"emerald":{"egg":[],"level-up":[["extreme-speed","49"],["odor-sleuth","1"],["bite","1"],["ember","1"],["roar","1"]],"machine":[["aerial-ace",""],["iron-tail",""],["strength",""],["protect",""],["return",""],["hidden-power",""],["double-team",""],["overheat",""],["attract",""],["dig",""],["fire-blast",""],["rock-smash",""],["flamethrower",""],["hyper-beam",""],["facade",""],["secret-power",""],["rest",""],["toxic",""],["roar",""],["frustration",""],["thief",""],["sunny-day",""]],"tutor":[["double-edge",""],["body-slam",""],["swagger",""],["endure",""],["mimic",""],["swift",""],["sleep-talk",""],["substitute",""],["snore",""]]},"firered-leafgreen":{"egg":[],"level-up":[["odor-sleuth","1"],["bite","1"],["ember","1"],["extreme-speed","49"],["roar","1"]],"machine":[["roar",""],["double-team",""],["attract",""],["flamethrower",""],["frustration",""],["rest",""],["dig",""],["aerial-ace",""],["iron-tail",""],["sunny-day",""],["facade",""],["return",""],["strength",""],["fire-blast",""],["toxic",""],["thief",""],["hidden-power",""],["rock-smash",""],["hyper-beam",""],["secret-power",""],["protect",""],["overheat",""]],"tutor":[["substitute",""],["body-slam",""],["mimic",""],["double-edge",""]]},"gold-silver":{"egg":[],"level-up":[["leer","1"],["flame-wheel","1"],["roar","1"],["extreme-speed","50"],["take-down","1"]],"machine":[["endure",""],["frustration",""],["dragon-breath",""],["double-team",""],["fire-blast",""],["rest",""],["swift",""],["hyper-beam",""],["roar",""],["headbutt",""],["snore",""],["toxic",""],["sunny-day",""],["swagger",""],["attract",""],["return",""],["rock-smash",""],["dig",""],["protect",""],["curse",""],["sleep-talk",""],["iron-tail",""],["hidden-power",""]],"tutor":[]},"heartgold-soulsilver":{"egg":[],"level-up":[["roar","1"],["extreme-speed","39"],["fire-fang","1"],["bite","1"],["odor-sleuth","1"],["thunder-fang","1"]],"machine":[["hidden-power",""],["fire-blast",""],["rock-climb",""],["secret-power",""],["endure",""],["return",""],["rock-smash",""],["frustration",""],["aerial-ace",""],["toxic",""],["will-o-wisp",""],["hyper-beam",""],["giga-impact",""],["facade",""],["double-team",""],["sunny-day",""],["solar-beam",""],["overheat",""],["captivate",""],["roar",""],["strength",""],["iron-tail",""],["swagger",""],["flamethrower",""],["dig",""],["attract",""],["rest",""],["dragon-pulse",""],["protect",""],["sleep-talk",""],["natural-gift",""],["substitute",""],["thief",""]],"tutor":[["swift",""],["mud-slap",""],["heat-wave",""],["helping-hand",""],["iron-head",""],["snore",""],["headbutt",""]]},"lets-go-pikachu-lets-go-eevee":{"egg":[],"level-up":[["roar","1"],["double-edge","1"],["bite","1"],["ember","1"],["leer","1"]],"machine":[["helping-hand",""],["headbutt",""],["hyper-beam",""],["rest",""],["will-o-wisp",""],["fire-blast",""],["reflect",""],["substitute",""],["superpower",""],["toxic",""],["teleport",""],["flamethrower",""],["dragon-pulse",""],["dig",""],["iron-tail",""],["play-rough",""],["outrage",""],["protect",""],["solar-beam",""],["facade",""]],"tutor":[]},"omega-ruby-alpha-sapphire":{"egg":[],"level-up":[["thunder-fang","1"],["extreme-speed","34"],["roar","1"],["bite","1"],["odor-sleuth","1"],["fire-fang","1"]],"machine":[["aerial-ace",""],["return",""],["retaliate",""],["safeguard",""],["wild-charge",""],["flamethrower",""],["swagger",""],["sunny-day",""],["roar",""],["fire-blast",""],["sleep-talk",""],["dig",""],["attract",""],["overheat",""],["flame-charge",""],["frustration",""],["secret-power",""],["protect",""],["substitute",""],["hidden-power",""],["incinerate",""],["will-o-wisp",""],["hyper-beam",""],["facade",""],["rest",""],["round",""],["giga-impact",""],["snarl",""],["confide",""],["toxic",""],["strength",""],["bulldoze",""],["double-team",""],["rock-smash",""],["solar-beam",""],["thief",""]],"tutor":[["iron-tail",""],["heat-wave",""],["outrage",""],["iron-head",""],["dragon-pulse",""],["snore",""],["covet",""],["helping-hand",""]]},"platinum":{"egg":[],"level-up":[["roar","1"],["extreme-speed","39"],["fire-fang","1"],["thunder-fang","1"],["odor-sleuth","1"],["bite","1"]],"machine":[["sleep-talk",""],["strength",""],["double-team",""],["facade",""],["rock-smash",""],["swagger",""],["overheat",""],["solar-beam",""],["hyper-beam",""],["iron-tail",""],["will-o-wisp",""],["return",""],["attract",""],["substitute",""],["endure",""],["fire-blast",""],["rest",""],["dig",""],["sunny-day",""],["natural-gift",""],["captivate",""],["thief",""],["frustration",""],["flamethrower",""],["aerial-ace",""],["dragon-pulse",""],["roar",""],["rock-climb",""],["toxic",""],["protect",""],["secret-power",""],["hidden-power",""],["giga-impact",""]],"tutor":[["iron-head",""],["swift",""],["snore",""],["mud-slap",""],["heat-wave",""],["helping-hand",""]]},"red-blue":{"egg":[],"level-up":[["ember","1"],["take-down","1"],["roar","1"],["leer","1"]],"machine":[["dragon-rage",""],["hyper-beam",""],["toxic",""],["teleport",""],["swift",""],["take-down",""],["mimic",""],["substitute",""],["double-edge",""],["reflect",""],["fire-blast",""],["rage",""],["skull-bash",""],["body-slam",""],["dig",""],["bide",""],["double-team",""],["rest",""]],"tutor":[]},"ruby-sapphire":{"egg":[],"level-up":[["extreme-speed","49"],["ember","1"],["bite","1"],["odor-sleuth","1"],["roar","1"]],"machine":[["flamethrower",""],["toxic",""],["secret-power",""],["strength",""],["roar",""],["return",""],["double-team",""],["hyper-beam",""],["attract",""],["iron-tail",""],["sunny-day",""],["protect",""],["frustration",""],["rock-smash",""],["aerial-ace",""],["fire-blast",""],["rest",""],["thief",""],["hidden-power",""],["overheat",""],["dig",""],["facade",""]],"tutor":[]},"scarlet-violet":{"egg":[],"level-up":[["leer","1"],["roar","1"],["bite","1"],["fire-fang","1"],["ember","1"],["reversal","1"],["retaliate","1"],["play-rough","1"],["crunch","1"],["take-down","1"],["flare-blitz","1"],["agility","1"],["howl","1"],["flame-wheel","1"],["helping-hand","1"],["flamethrower","5"],["extreme-speed","0"]],"machine":[["reversal",""],["aerial-ace",""],["sleep-talk",""],["crunch",""],["fire-fang",""],["bulldoze",""],["heat-crash",""],["dig",""],["snarl",""],["tera-blast",""],["dragon-pulse",""],["iron-head",""],["scorching-sands",""],["substitute",""],["body-slam",""],["charm",""],["curse",""],["hyper-voice",""],["fire-blast",""],["rest",""],["endure",""],["hyper-beam",""],["flare-blitz",""],["roar",""],["swift",""],["play-rough",""],["flamethrower",""],["sunny-day",""],["temper-flare",""],["thunder-fang",""],["fire-spin",""],["scary-face",""],["close-combat",""],["outrage",""],["take-down",""],["overheat",""],["giga-impact",""],["helping-hand",""],["double-edge",""],["flame-charge",""],["wild-charge",""],["psychic-fangs",""],["agility",""],["will-o-wisp",""],["protect",""],["heat-wave",""],["thief",""],["facade",""],["solar-beam",""]],"tutor":[]},"sun-moon":{"egg":[],"level-up":[["extreme-speed","34"],["roar","1"],["odor-sleuth","1"],["fire-fang","1"],["bite","1"],["thunder-fang","1"]],"machine":[["rest",""],["giga-impact",""],["aerial-ace",""],["thief",""],["fire-blast",""],["substitute",""],["swagger",""],["protect",""],["facade",""],["attract",""],["bulldoze",""],["snarl",""],["round",""],["hidden-power",""],["hyper-beam",""],["flamethrower",""],["toxic",""],["safeguard",""],["double-team",""],["overheat",""],["solar-beam",""],["roar",""],["frustration",""],["sunny-day",""],["confide",""],["sleep-talk",""],["wild-charge",""],["flame-charge",""],["will-o-wisp",""],["return",""]],"tutor":[]},"sword-shield":{"egg":[],"level-up":[["burn-up","1"],["roar","1"],["flare-blitz","1"],["howl","1"],["play-rough","1"],["extreme-speed","1"],["flamethrower","1"],["retaliate","1"],["crunch","1"],["reversal","1"],["bite","1"],["extreme-speed","0"],["fire-fang","1"],["helping-hand","1"],["leer","1"],["agility","1"],["flame-wheel","1"],["ember","1"],["take-down","1"]],"machine":[["solar-beam",""],["will-o-wisp",""],["overheat",""],["hyper-beam",""],["agility",""],["sunny-day",""],["wild-charge",""],["snore",""],["heat-wave",""],["round",""],["retaliate",""],["snarl",""],["play-rough",""],["swift",""],["substitute",""],["fire-fang",""],["outrage",""],["thief",""],["iron-tail",""],["dig",""],["reversal",""],["endure",""],["fire-blast",""],["safeguard",""],["giga-impact",""],["attract",""],["scary-face",""],["body-slam",""],["protect",""],["sleep-talk",""],["flare-blitz",""],["fire-spin",""],["close-combat",""],["thunder-fang",""],["iron-head",""],["hyper-voice",""],["crunch",""],["flamethrower",""],["rest",""],["helping-hand",""],["bulldoze",""],["dragon-pulse",""],["facade",""],["psychic-fangs",""]],"tutor":[["scorching-sands",""]]},"ultra-sun-ultra-moon":{"egg":[],"level-up":[["roar","1"],["thunder-fang","1"],["bite","1"],["extreme-speed","34"],["fire-fang","1"],["odor-sleuth","1"]],"machine":[["flame-charge",""],["sleep-talk",""],["wild-charge",""],["hyper-beam",""],["frustration",""],["substitute",""],["sunny-day",""],["fire-blast",""],["round",""],["hidden-power",""],["giga-impact",""],["roar",""],["solar-beam",""],["toxic",""],["return",""],["facade",""],["will-o-wisp",""],["protect",""],["flamethrower",""],["aerial-ace",""],["thief",""],["overheat",""],["rest",""],["snarl",""],["swagger",""],["confide",""],["safeguard",""],["bulldoze",""],["attract",""],["double-team",""]],"tutor":[["iron-tail",""],["snore",""],["laser-focus",""],["outrage",""],["helping-hand",""],["heat-wave",""],["covet",""],["dragon-pulse",""],["iron-head",""]]},"x-y":{"egg":[],"level-up":[["thunder-fang","1"],["roar","1"],["fire-fang","1"],["extreme-speed","34"],["bite","1"],["odor-sleuth","1"]],"machine":[["retaliate",""],["rest",""],["flamethrower",""],["solar-beam",""],["frustration",""],["bulldoze",""],["protect",""],["sleep-talk",""],["round",""],["will-o-wisp",""],["rock-smash",""],["thief",""],["hyper-beam",""],["snarl",""],["facade",""],["safeguard",""],["roar",""],["substitute",""],["toxic",""],["sunny-day",""],["strength",""],["dig",""],["hidden-power",""],["double-team",""],["overheat",""],["attract",""],["swagger",""],["flame-charge",""],["confide",""],["incinerate",""],["return",""],["fire-blast",""],["aerial-ace",""],["wild-charge",""],["giga-impact",""]],"tutor":[]},"xd":{"egg":[],"level-up":[["roar","1"],["extreme-speed","49"],["bite","1"],["ember","1"],["odor-sleuth","1"]],"machine":[["iron-tail",""],["rock-smash",""],["facade",""],["frustration",""],["sunny-day",""],["secret-power",""],["protect",""],["return",""],["dig",""],["hidden-power",""],["overheat",""],["thief",""],["aerial-ace",""],["double-team",""],["fire-blast",""],["hyper-beam",""],["rest",""],["flamethrower",""],["attract",""],["roar",""],["toxic",""],["strength",""]],"tutor":[["swagger",""],["substitute",""],["body-slam",""],["mimic",""],["double-edge",""]]},"yellow":{"egg":[],"level-up":[["leer","1"],["ember","1"],["take-down","1"],["roar","1"]],"machine":[["teleport",""],["mimic",""],["rest",""],["hyper-beam",""],["skull-bash",""],["double-edge",""],["fire-blast",""],["bide",""],["dig",""],["rage",""],["take-down",""],["substitute",""],["toxic",""],["body-slam",""],["reflect",""],["double-team",""],["dragon-rage",""],["swift",""]],"tutor":[]}},"name":"arcanine","types":["fire"],"weight":1550}