{"abilities":["frisk","competitive"],"base_stats":["45","30","50","55","65","45"],"evolution_chain_id":293,"evs":["0","0","0","0","1","0"],"front_female_sprite_default":"No female sprite default found.","front_female_sprite_shiny":"No female sprite shiny found.","front_sprite_default":"https://raw.githubusercontent.com/PokeAPI/sprites/master/sprites/pokemon/574.png","front_sprite_shiny":"https://raw.githubusercontent.com/PokeAPI/sprites/master/sprites/pokemon/shiny/574.png","games":["x","black","omega","sword","sun","ultra","scarlet"],"height":4,"hidden_ability":"shadow-tag","id":574,"moves":{"black-2-white-2":{"egg":[["mean-look",""],["miracle-eye",""],["uproar",""],["dark-pulse",""],["captivate",""],["mirror-coat",""]],"level-up":[["embargo","19"],["pound","1"],["feint-attack","24"],["flatter","28"],["psychic","37"],["telekinesis","40"],["charm","46"],["magic-room","48"],["psyshock","25"],["tickle","7"],["psybeam","16"],["confusion","3"],["fake-tears","10"],["heal-block","33"],["future-sight","31"],["double-slap","14"]],"machine":[["taunt",""],["psychic",""],["energy-ball",""],["toxic",""],["thunderbolt",""],["attract",""],["protect",""],["swagger",""],["trick-room",""],["telekinesis",""],["payback",""],["torment",""],["reflect",""],["psyshock",""],["psych-up",""],["shadow-ball",""],["facade",""],["return",""],["thunder-wave",""],["light-screen",""],["flash",""],["thief",""],["rest",""],["calm-mind",""],["double-team",""],["safeguard",""],["hidden-power",""],["embargo",""],["substitute",""],["fling",""],["grass-knot",""],["charge-beam",""],["rock-tomb",""],["rock-slide",""],["frustration",""],["dream-eater",""],["rain-dance",""],["round",""]],"tutor":[["helping-hand",""],["magic-coat",""],["uproar",""],["trick",""],["skill-swap",""],["foul-play",""],["heal-bell",""],["gravity",""],["snore",""],["zen-headbutt",""],["signal-beam",""],["covet",""],["magic-room",""],["role-play",""],["snatch",""],["recycle",""],["sleep-talk",""]]},"black-white":{"egg":[["captivate",""],["uproar",""],["dark-pulse",""],["miracle-eye",""],["mean-look",""],["mirror-coat",""]],"level-up":[["telekinesis","40"],["feint-attack","24"],["fake-tears","10"],["psychic","37"],["magic-room","48"],["psybeam","16"],["charm","46"],["flatter","28"],["heal-block","33"],["confusion","3"],["embargo","19"],["pound","1"],["double-slap","14"],["tickle","7"],["future-sight","31"],["psyshock","25"]],"machine":[["torment",""],["rock-tomb",""],["attract",""],["psyshock",""],["reflect",""],["frustration",""],["fling",""],["swagger",""],["thunderbolt",""],["light-screen",""],["thunder-wave",""],["shadow-ball",""],["psychic",""],["rock-slide",""],["hidden-power",""],["taunt",""],["dream-eater",""],["round",""],["trick-room",""],["thief",""],["safeguard",""],["double-team",""],["rest",""],["toxic",""],["facade",""],["telekinesis",""],["flash",""],["rain-dance",""],["charge-beam",""],["embargo",""],["energy-ball",""],["substitute",""],["protect",""],["payback",""],["grass-knot",""],["psych-up",""],["return",""],["calm-mind",""]],"tutor":[]},"omega-ruby-alpha-sapphire":{"egg":[["captivate",""],["mean-look",""],["mirror-coat",""],["miracle-eye",""],["dark-pulse",""],["heal-pulse",""],["uproar",""]],"level-up":[["tickle","7"],["psychic","37"],["heal-block","33"],["pound","1"],["play-nice","8"],["psybeam","16"],["flatter","28"],["feint-attack","24"],["magic-room","48"],["confusion","3"],["future-sight","31"],["charm","46"],["double-slap","14"],["psyshock","25"],["telekinesis","40"],["embargo","19"],["fake-tears","10"]],"machine":[["rock-slide",""],["dark-pulse",""],["flash",""],["thief",""],["attract",""],["light-screen",""],["swagger",""],["rain-dance",""],["charge-beam",""],["return",""],["hidden-power",""],["double-team",""],["torment",""],["thunderbolt",""],["psychic",""],["frustration",""],["safeguard",""],["secret-power",""],["round",""],["dream-eater",""],["sleep-talk",""],["rock-tomb",""],["rest",""],["payback",""],["energy-ball",""],["taunt",""],["protect",""],["substitute",""],["psych-up",""],["facade",""],["shadow-ball",""],["embargo",""],["trick-room",""],["grass-knot",""],["reflect",""],["psyshock",""],["toxic",""],["confide",""],["calm-mind",""],["fling",""],["thunder-wave",""]],"tutor":[["uproar",""],["magic-room",""],["foul-play",""],["role-play",""],["zen-headbutt",""],["recycle",""],["magic-coat",""],["shock-wave",""],["skill-swap",""],["helping-hand",""],["snatch",""],["covet",""],["snore",""],["trick",""],["signal-beam",""],["heal-bell",""],["gravity",""]]},"scarlet-violet":{"egg":[["mean-look",""],["mirror-coat",""],["heal-pulse",""],["torment",""],["fake-out",""]],"level-up":[["tickle","8"],["psybeam","12"],["future-sight","44"],["play-nice","4"],["fake-tears","28"],["confusion","1"],["magic-room","48"],["psych-up","33"],["charm","16"],["flatter","40"],["psyshock","20"],["hypnosis","24"],["pound","1"],["psychic","36"]],"machine":[["stored-power",""],["substitute",""],["endure",""],["zen-headbutt",""],["thunderbolt",""],["psyshock",""],["expanding-force",""],["charm",""],["trick",""],["rain-dance",""],["thief",""],["reflect",""],["future-sight",""],["rock-tomb",""],["swift",""],["thunder-wave",""],["psybeam",""],["protect",""],["psych-up",""],["imprison",""],["gravity",""],["nasty-plot",""],["trick-room",""],["foul-play",""],["psychic-terrain",""],["taunt",""],["rock-slide",""],["facade",""],["fake-tears",""],["fling",""],["psychic",""],["light-screen",""],["helping-hand",""],["sleep-talk",""],["skill-swap",""],["grass-knot",""],["dark-pulse",""],["tera-blast",""],["shadow-ball",""],["rest",""],["calm-mind",""],["energy-ball",""],["psychic-noise",""]],"tutor":[]},"sun-moon":{"egg":[["miracle-eye",""],["heal-pulse",""],["dark-pulse",""],["mirror-coat",""],["captivate",""],["mean-look",""],["uproar",""]],"level-up":[["psyshock","25"],["future-sight","31"],["telekinesis","40"],["tickle","7"],["embargo","19"],["double-slap","14"],["flatter","28"],["play-nice","8"],["charm","46"],["feint-attack","24"],["confusion","3"],["magic-room","48"],["psybeam","16"],["psychic","37"],["fake-tears","10"],["pound","1"],["heal-block","33"]],"machine":[["substitute",""],["dream-eater",""],["facade",""],["calm-mind",""],["thief",""],["psyshock",""],["frustration",""],["grass-knot",""],["light-screen",""],["taunt",""],["dark-pulse",""],["reflect",""],["protect",""],["return",""],["toxic",""],["thunderbolt",""],["thunder-wave",""],["attract",""],["safeguard",""],["hidden-power",""],["sleep-talk",""],["psych-up",""],["charge-beam",""],["psychic",""],["shadow-ball",""],["embargo",""],["energy-ball",""],["confide",""],["rock-tomb",""],["double-team",""],["trick-room",""],["swagger",""],["round",""],["torment",""],["payback",""],["rock-slide",""],["rain-dance",""],["rest",""],["fling",""]],"tutor":[]},"sword-shield":{"egg":[["heal-pulse",""],["mirror-coat",""],["mean-look",""],["fake-out",""],["torment",""]],"level-up":[["magic-room","48"],["play-nice","4"],["psych-up","33"],["pound","1"],["future-sight","44"],["hypnosis","24"],["flatter","40"],["tickle","8"],["fake-tears","28"],["charm","16"],["psybeam","12"],["confusion","1"],["psychic","36"],["psyshock","20"]],"machine":[["fake-tears",""],["protect",""],["attract",""],["safeguard",""],["rain-dance",""],["trick",""],["substitute",""],["thunder-wave",""],["shadow-ball",""],["calm-mind",""],["trick-room",""],["psyshock",""],["endure",""],["foul-play",""],["round",""],["rock-tomb",""],["light-screen",""],["charm",""],["guard-swap",""],["thief",""],["payback",""],["sleep-talk",""],["energy-ball",""],["rest",""],["facade",""],["snore",""],["skill-swap",""],["dark-pulse",""],["grass-knot",""],["ally-switch",""],["taunt",""],["uproar",""],["rock-slide",""],["nasty-plot",""],["stored-power",""],["psychic",""],["thunderbolt",""],["future-sight",""],["fling",""],["zen-headbutt",""],["helping-hand",""],["reflect",""],["magic-room",""]],"tutor":[["expanding-force",""]]},"ultra-sun-ultra-moon":{"egg":[["heal-pulse",""],["mirror-coat",""],["mean-look",""],["uproar",""],["miracle-eye",""],["captivate",""],["dark-pulse",""]],"level-up":[["pound","1"],["fake-tears","10"],["play-nice","8"],["flatter","28"],["psyshock","25"],["future-sight","31"],["confusion","3"],["feint-attack","24"],["psybeam","16"],["telekinesis","40"],["double-slap","14"],["psychic","37"],["charm","46"],["embargo","19"],["heal-block","33"],["tickle","7"],["magic-room","48"]],"machine":[["thunder-wave",""],["psyshock",""],["frustration",""],["rock-tomb",""],["thief",""],["psychic",""],["calm-mind",""],["double-team",""],["dark-pulse",""],["trick-room",""],["substitute",""],["thunderbolt",""],["dream-eater",""],["energy-ball",""],["swagger",""],["rest",""],["attract",""],["taunt",""],["safeguard",""],["fling",""],["charge-beam",""],["hidden-power",""],["embargo",""],["protect",""],["rain-dance",""],["payback",""],["torment",""],["sleep-talk",""],["return",""],["psych-up",""],["round",""],["shadow-ball",""],["confide",""],["facade",""],["toxic",""],["reflect",""],["light-screen",""],["rock-slide",""],["grass-knot",""]],"tutor":[["telekinesis",""],["uproar",""],["snore",""],["gravity",""],["trick",""],["signal-beam",""],["magic-room",""],["ally-switch",""],["magic-coat",""],["helping-hand",""],["role-play",""],["shock-wave",""],["heal-bell",""],["recycle",""],["snatch",""],["zen-headbutt",""],["skill-swap",""],["covet",""],["foul-play",""]]},"x-y":{"egg":[["dark-pulse",""],["uproar",""],["mean-look",""],["mirror-coat",""],["captivate",""],["miracle-eye",""],["heal-pulse",""]],"level-up":[["confusion","3"],["magic-room","48"],["feint-attack","24"],["flatter","28"],["psybeam","16"],["future-sight","31"],["play-nice","8"],["pound","1"],["fake-tears","10"],["charm","46"],["psyshock","25"],["psychic","37"],["embargo","19"],["double-slap","14"],["tickle","7"],["heal-block","33"],["telekinesis","40"]],"machine":[["payback",""],["energy-ball",""],["charge-beam",""],["thief",""],["round",""],["rain-dance",""],["rock-slide",""],["rock-tomb",""],["grass-knot",""],["psychic",""],["thunderbolt",""],["protect",""],["dream-eater",""],["return",""],["sleep-talk",""],["psych-up",""],["trick-room",""],["shadow-ball",""],["confide",""],["toxic",""],["torment",""],["psyshock",""],["facade",""],["attract",""],["double-team",""],["flash",""],["embargo",""],["calm-mind",""],["hidden-power",""],["fling",""],["thunder-wave",""],["taunt",""],["light-screen",""],["reflect",""],["rest",""],["substitute",""],["safeguard",""],["swagger",""],["frustration",""]],"tutor":[]}},"name":"gothita","types":["psychic"],"weight":58}