{"abilities":["swarm","sheer-force"],"base_stats":["70","135","95","45","70","85"],"evolution_chain_id":58,"evs":["0","2","0","0","0","0"],"front_female_sprite_default":"No female sprite default found.","front_female_sprite_shiny":"No female sprite shiny found.","front_sprite_default":"https://raw.githubusercontent.com/PokeAPI/sprites/master/sprites/pokemon/900.png","front_sprite_shiny":"https://raw.githubusercontent.com/PokeAPI/sprites/master/sprites/pokemon/shiny/900.png","games":["scarlet"],"height":18,"hidden_ability":"sharpness","id":900,"moves":{"scarlet-violet":{"egg":[],"level-up":[["stone-axe","0"],["x-scissor","40"],["double-team","16"],["rock-slide","36"],["double-hit","20"],["leer","1"],["false-swipe","8"],["quick-attack","1"],["focus-energy","28"],["agility","32"],["slash","24"],["fury-cutter","4"],["smack-down","12"],["swords-dance","44"]],"machine":[["false-swipe",""],["swords-dance",""],["take-down",""],["air-cutter",""],["close-combat",""],["stealth-rock",""],["substitute",""],["smack-down",""],["struggle-bug",""],["tera-blast",""],["brick-break",""],["rock-tomb",""],["rock-blast",""],["light-screen",""],["rest",""],["acrobatics",""],["helping-hand",""],["sandstorm",""],["trailblaze",""],["sunny-day",""],["aerial-ace",""],["endure",""],["rock-slide",""],["bug-buzz",""],["double-edge",""],["skitter-smack",""],["agility",""],["hyper-beam",""],["dual-wingbeat",""],["baton-pass",""],["thief",""],["lunge",""],["stone-edge",""],["pounce",""],["facade",""],["tailwind",""],["u-turn",""],["x-scissor",""],["reversal",""],["swift",""],["bug-bite",""],["giga-impact",""],["scary-face",""],["air-slash",""],["vacuum-wave",""],["sleep-talk",""],["protect",""]],"tutor":[]}},"name":"kleavor","types":["bug","rock"],"weight":890}