{"abilities":["friend-guard","cheek-pouch"],"base_stats":["74","75","70","65","75","111"],"evolution_chain_id":485,"evs":["0","0","0","0","0","2"],"front_female_sprite_default":"No female sprite default found.","front_female_sprite_shiny":"No female sprite shiny found.","front_sprite_default":"https://raw.githubusercontent.com/PokeAPI/sprites/master/sprites/pokemon/925.png","front_sprite_shiny":"https://raw.githubusercontent.com/PokeAPI/sprites/master/sprites/pokemon/shiny/925.png","games":["scarlet"],"height":3,"hidden_ability":"technician","id":925,"moves":{"scarlet-violet":{"egg":[],"level-up":[["charm","37"],["pound","1"],["copycat","46"],["play-rough","29"],["super-fang","11"],["beat-up","41"],["bullet-seed","18"],["hyper-voice","33"],["tidy-up","1"],["double-hit","14"],["population-bomb","53"],["encore","22"],["baby-doll-eyes","1"],["helping-hand","8"],["follow-me","1"],["echoed-voice","5"]],"machine":[["low-kick",""],["bullet-seed",""],["sunny-day",""],["double-edge",""],["aerial-ace",""],["fake-tears",""],["rain-dance",""],["giga-impact",""],["taunt",""],["hyper-voice",""],["thunder-wave",""],["tera-blast",""],["sleep-talk",""],["rest",""],["endure",""],["low-sweep",""],["dig",""],["thief",""],["mud-slap",""],["substitute",""],["facade",""],["seed-bomb",""],["agility",""],["trailblaze",""],["shadow-claw",""],["protect",""],["swift",""],["encore",""],["helping-hand",""],["water-pulse",""],["super-fang",""],["hyper-beam",""],["chilling-water",""],["mud-shot",""],["take-down",""],["u-turn",""],["crunch",""],["grass-knot",""],["charm",""],["play-rough",""]],"tutor":[]}},"name":"maushold","types":["normal"],"weight":23}